MANIFEST.in
README.md
setup.py
streamlines/__init__.py
streamlines/read_write.py
streamlines.egg-info/PKG-INFO
streamlines.egg-info/SOURCES.txt
streamlines.egg-info/dependency_links.txt
streamlines.egg-info/top_level.txt