Metadata-Version: 1.0
Name: streamlines
Version: 0.0.2
Summary: Tools for working with files as line streams.
Home-page: https://github.com/jbn/streamlines
Author: John Bjorn Nelson
Author-email: jbn@abreka.com
License: License :: OSI Approved :: MIT License
Platform: UNKNOWN
